spheretrig/__init__.py
spheretrig/spheretrig.py
spheretrig/test.py
spheretrig-0.1.dist-info/LICENSE
spheretrig-0.1.dist-info/METADATA
spheretrig-0.1.dist-info/WHEEL
spheretrig-0.1.dist-info/top_level.txt
spheretrig-0.1.dist-info/RECORD
