Metadata-Version: 2.1
Name: spheretrig
Version: 0.1
Summary: spheretrig es un módulo de Python que proporciona clases y funciones para trabajar con trigonometría esférica.
Home-page: https://gitlab.com/pinpacho/Final_FCI
Author: Santiago Julio Davila, Julian Francisco Pinchao Ortiz, Andres Felipe Riaño Quintanilla
License: MIT
License-File: LICENSE
Requires-Dist: mpmath
Requires-Dist: numpy
Requires-Dist: packaging
Requires-Dist: plotly
Requires-Dist: sympy
Requires-Dist: tenacity
